datasesame-0.1.1.dist-info/METADATA
datasesame-0.1.1.dist-info/WHEEL
datasesame-0.1.1.dist-info/entry_points.txt
ds.libs/libgcc_s-5b5488a6.so.1
ds/main.py
ds/data.py
ds/__init__.py
ds/ds.cpython-312-arm-linux-musleabihf.so
datasesame-0.1.1.dist-info/RECORD
