Metadata-Version: 2.3
Name: datasesame
Version: 0.1.1
Classifier: Programming Language :: Rust
Classifier: Programming Language :: Python :: Implementation :: CPython
Classifier: Programming Language :: Python :: Implementation :: PyPy
Requires-Dist: rich
Requires-Dist: polars
Requires-Dist: scikit-learn
Requires-Dist: pytest ; extra == 'tests'
Provides-Extra: tests
Summary: CLI Tool for Easy Data Science
License: PolyForm Internal Use License 1.0.0
Requires-Python: >=3.8
